{
  "$schema": "https://developer.microsoft.com/json-schemas/fabric/item/report/definition/visualContainer/2.10.0/schema.json",
  "name": "sbPanel",
  "position": {
    "x": 0,
    "y": 0,
    "z": 1000,
    "height": 720,
    "width": 200,
    "tabOrder": 1000
  },
  "visual": {
    "visualType": "htmlContent443BE3AD55E043BF878BED274D3A6865",
    "query": {
      "queryState": {
        "content": {
          "projections": [
            {
              "field": {
                "Measure": {
                  "Expression": {
                    "SourceRef": {
                      "Entity": "_Medidas"
                    }
                  },
                  "Property": "HTML Sidebar"
                }
              },
              "queryRef": "_Medidas.HTML Sidebar",
              "nativeQueryRef": "HTML Sidebar"
            }
          ]
        }
      }
    },
    "drillFilterOtherVisuals": true
  }
}